diffdate/__init__.py
diffdate/diffdate.py
diffdate-0.0.6.dist-info/METADATA
diffdate-0.0.6.dist-info/WHEEL
diffdate-0.0.6.dist-info/entry_points.txt
diffdate-0.0.6.dist-info/licenses/LICENSE
diffdate-0.0.6.dist-info/RECORD
