Metadata-Version: 2.1
Name: diffdate
Version: 0.0.6
Summary: get the difference in days of two dates
Project-URL: Homepage, https://github.com/stephane-archer/diffdateproject
Project-URL: Bug Tracker, https://github.com/stephane-archer/diffdateproject/issues
Author-email: Fractale <archerstephane@gmail.com>
License-File: LICENSE
Classifier: License :: OSI Approved :: MIT License
Classifier: Operating System :: OS Independent
Classifier: Programming Language :: Python :: 3
Requires-Python: >=3.7
